iLaplace/__init__.py
iLaplace-4.2.1.dist-info/LICENCE.txt
iLaplace-4.2.1.dist-info/METADATA
iLaplace-4.2.1.dist-info/WHEEL
iLaplace-4.2.1.dist-info/top_level.txt
iLaplace-4.2.1.dist-info/RECORD
