Metadata-Version: 2.1
Name: iLaplace
Version: 4.2.1
Summary: A minimal Python interface for computing inverse Laplace transforms using Talbot’s method — designed as a clean and practical wrapper around sympy & mpmath
Home-page: 
Author: Mohammad Hossein Rostami
Author-email: MHRo.R84@GMAIL.Com
License: MIT
Keywords: laplace inverse,numerical inverse laplace transform,talbot method,mpmath,sympy,iLaplace
Classifier: Development Status :: 5 - Production/Stable
Classifier: Intended Audience :: Education
Classifier: Operating System :: Microsoft :: Windows :: Windows 10
Classifier: License :: OSI Approved :: MIT License
Classifier: Programming Language :: Python :: 3
License-File: LICENCE.txt
Requires-Dist: mpmath
Requires-Dist: sympy
